{
  "image": "ghcr.io/runlix/radarr",
  "version": "6.1.1.10360",
  "sha": "2dc68eb10b5efcb747b2fefe1c1c0a8bc0544173",
  "short_sha": "2dc68eb",
  "published_at": "2026-04-07T05:40:35Z",
  "manifests": [
    {
      "tag": "6.1.1.10360-debug",
      "digest": "sha256:83c7feaf056e6cfa2296bb04ffb52faed122986754a85ffca73d61b2be807e41",
      "platforms": [
        "linux/amd64",
        "linux/arm64"
      ]
    },
    {
      "tag": "6.1.1.10360-stable",
      "digest": "sha256:d6cf12984d64ccfad06f2da0e6d9a4bcf3c1e7a96c44ff2b9006da21437c0a8c",
      "platforms": [
        "linux/amd64",
        "linux/arm64"
      ]
    }
  ]
}
